pyhma/__init__.py
pyhma/nearest_image.py
pyhma/processor.py
pyhma/vasp_reader.py
pyhma-2.0.0.data/scripts/pyhma
pyhma-2.0.0.dist-info/METADATA
pyhma-2.0.0.dist-info/WHEEL
pyhma-2.0.0.dist-info/top_level.txt
pyhma-2.0.0.dist-info/RECORD
