Metadata-Version: 2.1
Name: pyhma
Version: 2.0.0
Summary: Python Distribution Utilities
Home-page: UNKNOWN
Author: Sabry Moustafa
Author-email: sabrygad@buffalo.edu
License: UNKNOWN
Platform: UNKNOWN
